smartsys_analyzer/__init__.py
smartsys_analyzer/config.py
smartsys_analyzer/core.py
smartsys_analyzer/utils.py
smartsys_analyzer-1.0.0.dist-info/licenses/LICENSE
smartsys_analyzer-1.0.0.dist-info/METADATA
smartsys_analyzer-1.0.0.dist-info/WHEEL
smartsys_analyzer-1.0.0.dist-info/top_level.txt
smartsys_analyzer-1.0.0.dist-info/RECORD
