Metadata-Version: 2.4
Name: smartsys-analyzer
Version: 1.0.0
Summary: Advanced system monitoring and analyzer toolkit for Python
Home-page: https://github.com/EdenGithhub/smartsys-analyzer
Author: Adam Alcander et Eden
Author-email: Adam Alcander et Eden <aeden6877@gmail.com>
License: MIT
Project-URL: Homepage, https://github.com/EdenGithhub/smartsys-analyzer
Project-URL: Issues, https://github.com/EdenGithhub/smartsys-analyzer/issues
Project-URL: Source, https://github.com/EdenGithhub/smartsys-analyzer
Keywords: monitoring,system,analyzer,CPU,memory,disk,health
Classifier: Development Status :: 5 - Production/Stable
Classifier: Intended Audience :: Developers
Classifier: License :: OSI Approved :: MIT License
Classifier: Operating System :: OS Independent
Classifier: Programming Language :: Python :: 3
Classifier: Programming Language :: Python :: 3.10
Classifier: Programming Language :: Python :: 3.11
Classifier: Topic :: System :: Monitoring
Requires-Python: >=3.6
License-File: LICENSE
Requires-Dist: pydantic>=2.0
Requires-Dist: psutil>=5.9
Requires-Dist: colorama>=0.4
Requires-Dist: rich>=13.0
Requires-Dist: playsound>=1.3
Requires-Dist: schedule
Requires-Dist: tabulate
Requires-Dist: matplotlib
Requires-Dist: humanize
Requires-Dist: pyyaml
Requires-Dist: jsonschema
Requires-Dist: typing-extensions
Requires-Dist: platformdirs
Requires-Dist: typer
Dynamic: author
Dynamic: home-page
Dynamic: license-file
Dynamic: requires-python
